comfygit_core/constants.py
comfygit_core/analyzers/config_comparison.py
comfygit_core/analyzers/custom_node_scanner.py
comfygit_core/analyzers/git_change_parser.py
comfygit_core/analyzers/model_scanner.py
comfygit_core/analyzers/node_classifier.py
comfygit_core/analyzers/node_git_analyzer.py
comfygit_core/analyzers/ref_diff_analyzer.py
comfygit_core/analyzers/status_scanner.py
comfygit_core/analyzers/workflow_dependency_parser.py
comfygit_core/caching/__init__.py
comfygit_core/caching/api_cache.py
comfygit_core/caching/base.py
comfygit_core/caching/comfyui_cache.py
comfygit_core/caching/custom_node_cache.py
comfygit_core/caching/workflow_cache.py
comfygit_core/clients/__init__.py
comfygit_core/clients/civitai_client.py
comfygit_core/clients/github_client.py
comfygit_core/clients/registry_client.py
comfygit_core/configs/comfyui_builtin_nodes.py
comfygit_core/configs/comfyui_models.py
comfygit_core/configs/model_config.py
comfygit_core/core/environment.py
comfygit_core/core/workspace.py
comfygit_core/factories/environment_factory.py
comfygit_core/factories/uv_factory.py
comfygit_core/factories/workspace_factory.py
comfygit_core/infrastructure/sqlite_manager.py
comfygit_core/integrations/__init__.py
comfygit_core/integrations/uv_command.py
comfygit_core/logging/logging_config.py
comfygit_core/managers/environment_git_orchestrator.py
comfygit_core/managers/environment_model_manager.py
comfygit_core/managers/export_import_manager.py
comfygit_core/managers/git_manager.py
comfygit_core/managers/model_download_manager.py
comfygit_core/managers/model_symlink_manager.py
comfygit_core/managers/node_manager.py
comfygit_core/managers/pyproject_manager.py
comfygit_core/managers/pytorch_backend_manager.py
comfygit_core/managers/system_node_symlink_manager.py
comfygit_core/managers/user_content_symlink_manager.py
comfygit_core/managers/uv_project_manager.py
comfygit_core/managers/workflow_manager.py
comfygit_core/merging/__init__.py
comfygit_core/merging/atomic_executor.py
comfygit_core-0.3.12.dist-info/METADATA
comfygit_core-0.3.12.dist-info/WHEEL
comfygit_core-0.3.12.dist-info/licenses/LICENSE.txt
comfygit_core-0.3.12.dist-info/RECORD
