Metadata-Version: 2.4
Name: comfygit-core
Version: 0.3.12
Summary: ComfyGit Core - Git-based ComfyUI environment manager
License-File: LICENSE.txt
Requires-Python: >=3.10
Requires-Dist: aiohttp>=3.9.0
Requires-Dist: blake3>=1.0.5
Requires-Dist: packaging>=25.0
Requires-Dist: psutil>=7.0.0
Requires-Dist: pyyaml>=6.0
Requires-Dist: requests>=2.32.4
Requires-Dist: requirements-parser>=0.13.0
Requires-Dist: tomlkit>=0.13.3
Requires-Dist: uv>=0.7
Requires-Dist: xxhash>=2.0.0
